kssanalysis/__init__.py
kssanalysis-0.3.data/data/NEGATIVE.txt
kssanalysis-0.3.data/data/POSITIVE.txt
kssanalysis-0.3.dist-info/LICENCE.txt.txt
kssanalysis-0.3.dist-info/METADATA
kssanalysis-0.3.dist-info/WHEEL
kssanalysis-0.3.dist-info/top_level.txt
kssanalysis-0.3.dist-info/RECORD
