Metadata-Version: 2.1
Name: kssanalysis
Version: 0.3
Summary: This file is responsible to return the context of word
Home-page: https://github.com/kailash01/kssanalysis
Author: Kailash, Sudhanshu
Author-email: kumar.rajiv09876@gmail.com, sudhshreya666@gmail.com
License: UNKNOWN
Platform: UNKNOWN
